lsdnumbatools/HCL.py
lsdnumbatools/_SFchannel_network.py
lsdnumbatools/__init__.py
lsdnumbatools/_looper.py
lsdnumbatools/_mask_tools.py
lsdnumbatools/_node_graph.py
lsdnumbatools/_union_find.py
lsdnumbatools/channel_network.py
lsdnumbatools/cli.py
lsdnumbatools/drainage_divide_tools.py
lsdnumbatools/flow_metrics.py
lsdnumbatools/graph.py
lsdnumbatools/hill_metrics.py
lsdnumbatools/lsd_exceptions.py
lsdnumbatools/lsdnbtools_flip_raster.py
lsdnumbatools/lsdnumbatools.py
lsdnumbatools/mask_tools.py
lsdnumbatools/node_graph.py
lsdnumbatools/priority_queue.py
lsdnumbatools/quick_lem.py
lsdnumbatools/quicktempstuff.py
lsdnumbatools/utils.py
lsdnumbatools/xarray_lsdtt.py
lsdnumbatools-0.0.5.dist-info/AUTHORS.rst
lsdnumbatools-0.0.5.dist-info/LICENSE
lsdnumbatools-0.0.5.dist-info/METADATA
lsdnumbatools-0.0.5.dist-info/WHEEL
lsdnumbatools-0.0.5.dist-info/entry_points.txt
lsdnumbatools-0.0.5.dist-info/top_level.txt
lsdnumbatools-0.0.5.dist-info/RECORD
