Metadata-Version: 2.1
Name: lsdnumbatools
Version: 0.0.5
Summary: Provides numba framework for topographic analysis within the LSDTopoTools ecosystem. It aims to provdide full python access to the main algorithms of LSDTopoTools while avoiding the neeeds of c++. It does not replace or provide numba portage of the full LSDTopoTools, just the main one for quick use or quick developments
Home-page: https://github.com/bgailleton/lsdnumbatools
Author: Boris Gailleton
Author-email: boris.gailleton@gfz-potsdam.de
License: MIT license
Keywords: lsdnumbatools
Platform: UNKNOWN
Classifier: Development Status :: 2 - Pre-Alpha
Classifier: Intended Audience :: Developers
Classifier: License :: OSI Approved :: MIT License
Classifier: Natural Language :: English
Classifier: Programming Language :: Python :: 3
Classifier: Programming Language :: Python :: 3.5
Classifier: Programming Language :: Python :: 3.6
Classifier: Programming Language :: Python :: 3.7
Classifier: Programming Language :: Python :: 3.8
Requires-Python: >=3.5
Requires-Dist: Click (>=7.0)
